bran/__init__.py
bran/hash.py
bran/util.py
bran-0.4.0.dist-info/METADATA
bran-0.4.0.dist-info/RECORD
bran-0.4.0.dist-info/WHEEL
bran-0.4.0.dist-info/top_level.txt
bran-0.4.0.dist-info/zip-safe
