Metadata-Version: 2.1
Name: bran
Version: 0.4.0
Summary: DER-Encoded ASN.1 Serialization and Deserialization
Home-page: https://github.com/jfinkhaeuser/bran
Author: Jens Finkhaeuser
Author-email: jens@finkhaeuser.de
License: MITNFA
Keywords: ASN.1 DER serialization
Platform: UNKNOWN
Classifier: Development Status :: 4 - Beta
Classifier: Environment :: Plugins
Classifier: Intended Audience :: Developers
Classifier: License :: OSI Approved :: MIT License
Classifier: Natural Language :: English
Classifier: Operating System :: OS Independent
Classifier: Programming Language :: Python :: 2
Classifier: Programming Language :: Python :: 2.7
Classifier: Programming Language :: Python :: 3
Classifier: Programming Language :: Python :: 3.4
Classifier: Programming Language :: Python :: 3.5
Classifier: Programming Language :: Python :: 3.6
Classifier: Topic :: Security :: Cryptography
Classifier: Topic :: Software Development :: Libraries :: Python Modules
Provides-Extra: dev
Requires-Dist: six (~=1.11)
Requires-Dist: pyasn1 (~=0.4)
Provides-Extra: dev
Requires-Dist: tox (>=2.8); extra == 'dev'
Requires-Dist: bump2version (>=0.5); extra == 'dev'
Requires-Dist: pytest (>=3.2); extra == 'dev'
Requires-Dist: pytest-cov (>=2.5); extra == 'dev'
Requires-Dist: flake8 (>=3.4); extra == 'dev'
Requires-Dist: pep8-naming (>=0.4); extra == 'dev'
Requires-Dist: flake8-quotes (>=0.11); extra == 'dev'
Requires-Dist: flake8-docstrings (>=1.1); extra == 'dev'
Requires-Dist: sphinx (>=1.6); extra == 'dev'
